vid_cleaner/__init__.py
vid_cleaner/config.py
vid_cleaner/constants.py
vid_cleaner/default_config.toml
vid_cleaner/vidcleaner.py
vid_cleaner/cli/__init__.py
vid_cleaner/cli/cache.py
vid_cleaner/cli/clean_video.py
vid_cleaner/cli/clip_video.py
vid_cleaner/cli/inspect_video.py
vid_cleaner/cli/search.py
vid_cleaner/controllers/__init__.py
vid_cleaner/controllers/temp_files.py
vid_cleaner/models/__init__.py
vid_cleaner/models/video_file.py
vid_cleaner/utils/__init__.py
vid_cleaner/utils/api_utils.py
vid_cleaner/utils/cli.py
vid_cleaner/utils/ffmpeg_utils.py
vid_cleaner/views/__init__.py
vid_cleaner/views/tables.py
vid_cleaner-0.7.4.dist-info/METADATA
vid_cleaner-0.7.4.dist-info/WHEEL
vid_cleaner-0.7.4.dist-info/entry_points.txt
vid_cleaner-0.7.4.dist-info/licenses/LICENSE
vid_cleaner-0.7.4.dist-info/RECORD
