Metadata-Version: 2.4
Name: vid-cleaner
Version: 0.7.4
Summary: Tools to transcode, inspect and convert videos.
Project-URL: Homepage, https://github.com/natelandau/vid-cleaner
Project-URL: Repository, https://github.com/natelandau/vid-cleaner
Author-email: Nate Landau <github@natenate.org>
License:                     GNU AFFERO GENERAL PUBLIC LICENSE
License-File: LICENSE
Classifier: Programming Language :: Python :: 3.11
Classifier: Programming Language :: Python :: 3.12
Classifier: Programming Language :: Python :: 3.13
Classifier: Programming Language :: Python :: 3.14
Requires-Python: >=3.11
Requires-Dist: cappa>=0.30.0
Requires-Dist: dynaconf>=3.2.11
Requires-Dist: ffmpeg-progress-yield>=1.0.1
Requires-Dist: ffmpeg-progress>=0.0.5
Requires-Dist: ffmpeg-python>=0.2.0
Requires-Dist: httpx>=0.28.1
Requires-Dist: iso639-lang>=2.6.3
Requires-Dist: nclutils>=2.1.0
Requires-Dist: python-box>=7.3.2
Requires-Dist: rich>=14.1.0
Requires-Dist: validators>=0.35.0
